file_util/__init__.py
file_util/file_util.py
file_util_deepsec-1.0.0.dist-info/LICENSE
file_util_deepsec-1.0.0.dist-info/METADATA
file_util_deepsec-1.0.0.dist-info/WHEEL
file_util_deepsec-1.0.0.dist-info/top_level.txt
file_util_deepsec-1.0.0.dist-info/RECORD
